syzgy/__init__.py
syzgy/client.py
syzgy/exceptions.py
syzgy/models.py
syzgy-0.1.0.dist-info/METADATA
syzgy-0.1.0.dist-info/WHEEL
syzgy-0.1.0.dist-info/top_level.txt
syzgy-0.1.0.dist-info/RECORD
