Metadata-Version: 2.1
Name: syzgy
Version: 0.1.0
Summary: A Python client for the SyzgyDB vector database
Home-page: https://github.com/smhanov/syzgydb
Author: Steve Hanov
Author-email: steve.hanov@gmail.com
Classifier: Development Status :: 3 - Alpha
Classifier: Intended Audience :: Developers
Classifier: License :: OSI Approved :: MIT License
Classifier: Operating System :: OS Independent
Classifier: Programming Language :: Python :: 3
Classifier: Programming Language :: Python :: 3.7
Classifier: Programming Language :: Python :: 3.8
Classifier: Programming Language :: Python :: 3.9
Requires-Python: >=3.5
Requires-Dist: requests>=2.25.0
